swarms_utils/__init__.py
swarms_utils/json_former.py
swarms_utils/logits_processor.py
swarms_utils/swarm_matcher.py
swarms_utils-0.1.0.dist-info/LICENSE
swarms_utils-0.1.0.dist-info/METADATA
swarms_utils-0.1.0.dist-info/WHEEL
swarms_utils-0.1.0.dist-info/RECORD
